{"groupId":59,"groupName":"QBF","talks":[{"abstractId":1541,"title":"Invited Talk - Dependency Schemes from Antiquity to Modernity","authors":"Tom\u00E1\u0161 Peitl","chairs":"Tony Tan","abstract":"","sessionName":"Pragmatics of QBF","day":"19/07/2026","startTime":"09:00","affiliations":["TU Wien"],"href":"QBF-2026-07-19.html#talk:1541"},{"abstractId":1542,"title":"Certification of True QBF Formulas in Expansion-Based Solving","authors":"Sidhant Bhavnani, Clemens Hofstadler, Martina Seidl","chairs":"Tony Tan","abstract":"","sessionName":"Pragmatics of QBF","day":"19/07/2026","startTime":"09:00","affiliations":["Johannes Kepler University - Linz"],"href":"QBF-2026-07-19.html#talk:1542"},{"abstractId":1543,"title":"Solving Connect Four with QBF: The Progress So Far","authors":"Valentin Mayer-Eichberger, Abdallah Saffidine","chairs":"Tony Tan","abstract":"","sessionName":"Pragmatics of QBF","day":"19/07/2026","startTime":"09:00","affiliations":["University of Potsdam, Potsdam, Germany","Potassco Solutions, Potsdam, Germany"],"href":"QBF-2026-07-19.html#talk:1543"},{"abstractId":1544,"title":"Strengthening the Implication-Free DQBF Dependency Scheme","authors":"Ralf Wimmer, Christoph Scholl, Franz-Xaver Reichl","chairs":"Leroy Chew","abstract":"","sessionName":"Dependency QBF","day":"19/07/2026","startTime":"10:50","affiliations":["Altair Engineering GmbH","University of Freiburg"],"href":"QBF-2026-07-19.html#talk:1544"},{"abstractId":1545,"title":"Symmetry Breaking in Dependency Quantified Boolean Formulas","authors":"Paul Seip, Clemens Hofstadler, Manuel Kauers, Martina Seidl","chairs":"Leroy Chew","abstract":"","sessionName":"Dependency QBF","day":"19/07/2026","startTime":"10:50","affiliations":["JKU Linz"],"href":"QBF-2026-07-19.html#talk:1545"},{"abstractId":1546,"title":"On the Practicality of DQBF Solving for Succinctly Represented Graph Problems","authors":"Chen-Ching Nieh, Chi-Kit Ng, Jie-Hong R. Jiang, Tony Tan","chairs":"Leroy Chew","abstract":"","sessionName":"Dependency QBF","day":"19/07/2026","startTime":"10:50","affiliations":["National Taiwan University","University of Liverpool"],"href":"QBF-2026-07-19.html#talk:1546"},{"abstractId":1547,"title":"QBF Gallery","authors":"Martina Seidl, Cynthia Peyrer, Luca Pulina","chairs":"Leroy Chew","abstract":"","sessionName":"Dependency QBF","day":"19/07/2026","startTime":"10:50","affiliations":["JKU","University of Sassari"],"href":"QBF-2026-07-19.html#talk:1547"},{"abstractId":1548,"title":"Invited Talk - The Complexity of Quantified CDCL","authors":"Benjamin B\u00F6hm","chairs":"Lea Kasche","abstract":"","sessionName":"QBF Proof Complexity (PC and QBF Joint Session)","day":"19/07/2026","startTime":"14:00","affiliations":["University of Jena"],"href":"QBF-2026-07-19.html#talk:1548"},{"abstractId":1549,"title":"Quantified CDCL and Dependency Schemes: A proof-theoretic study","authors":"Abhimanyu Choudhury, Meena Mahajan","chairs":"Lea Kasche","abstract":"","sessionName":"QBF Proof Complexity (PC and QBF Joint Session)","day":"19/07/2026","startTime":"14:00","affiliations":["IIT Bombay","The Institute of Mathematical Sciences, Homi Bhabha National Institute"],"href":"QBF-2026-07-19.html#talk:1549"},{"abstractId":1550,"title":"A Boolean static proof system for Quantified Boolean Formulas.","authors":"Jan Johannsen, Marc Vinyals","chairs":"Lea Kasche","abstract":"","sessionName":"QBF Proof Complexity (PC and QBF Joint Session)","day":"19/07/2026","startTime":"14:00","affiliations":["LMU","University of Auckland"],"href":"QBF-2026-07-19.html#talk:1550"},{"abstractId":1551,"title":"A QBF-like Fragment of EPR","authors":"Leroy Chew, Mikol\u00E1\u0161 Janota, Martin Suda, Miroslav Ol\u0161\u00E1k","chairs":"Lea Kasche","abstract":"","sessionName":"QBF Proof Complexity (PC and QBF Joint Session)","day":"19/07/2026","startTime":"14:00","affiliations":["Czech Institute of Informatics Robotics and Cybernetics"],"href":"QBF-2026-07-19.html#talk:1551"},{"abstractId":1552,"title":"On Knowledge Compilation Languages for QBFs","authors":"Sravanthi Chede, Vaibhav Krishan, Swagato Sanyal, Anil Shukla","chairs":"Franz Reichl","abstract":"","sessionName":"QBF Counting, Sampling and Synthesis","day":"19/07/2026","startTime":"16:10","affiliations":["The Institute of Mathematical Sciences (A CI of Homi Bhabha National Institute), Chennai, India","School of Computer Science, The University of Sheffield, Sheffield, United Kingdom","Indian Institute of Technology Ropar, Rupnagar, India"],"href":"QBF-2026-07-19.html#talk:1552"},{"abstractId":1553,"title":"Solution-based QBF Equivalences And How To Check Them","authors":"Peter Pfeiffer","chairs":"Franz Reichl","abstract":"","sessionName":"QBF Counting, Sampling and Synthesis","day":"19/07/2026","startTime":"16:10","affiliations":["Johannes Kepler University Linz"],"href":"QBF-2026-07-19.html#talk:1553"},{"abstractId":1554,"title":"Exploring Toda\u0027s Theorem as a QBF Solver","authors":"Dror Fried, Etay Segal, Gad E. Yaron","chairs":"Franz Reichl","abstract":"","sessionName":"QBF Counting, Sampling and Synthesis","day":"19/07/2026","startTime":"16:10","affiliations":["The Open University of Israel, Ra\u0027anana, Israel","The Hebrew University of Jerusalem, The Open University of Israel"],"href":"QBF-2026-07-19.html#talk:1554"},{"abstractId":1555,"title":"Revisiting Encodings of Bounded Synthesis","authors":"Che Cheng, Long-Hin Fung, Jie-Hong Roland Jiang, Friedrich Slivovsky, Tony Tan","chairs":"Franz Reichl","abstract":"","sessionName":"QBF Counting, Sampling and Synthesis","day":"19/07/2026","startTime":"16:10","affiliations":["National Taiwan University","University of Liverpool"],"href":"QBF-2026-07-19.html#talk:1555"}]}