{"groupId":24,"groupName":"DPSOLVE\u002726","talks":[{"abstractId":656,"title":"Introduction to Domain Independent Dynamic Programming Algorithms","authors":"Christopher Beck","abstract":"","sessionName":"Introduction","day":"18/07/2026","startTime":"09:00","affiliations":["University of Toronto"],"href":"DPSOLVE-2026-07-18.html#talk:656"},{"abstractId":657,"title":"Decision Diagram-Based Branch-and-Bound Solvers","authors":"Willem-Jan van Hoeve","abstract":"","sessionName":"Introduction","day":"18/07/2026","startTime":"09:00","affiliations":["University of Toronto"],"href":"DPSOLVE-2026-07-18.html#talk:657"},{"abstractId":658,"title":"Neural Self-Improvement Learning for Domain-Independent Dynamic Programming","authors":"Minori Narita, Eldan Cohen, Chris Beck","abstract":"","sessionName":"Talks 1","day":"18/07/2026","startTime":"11:00","affiliations":["University of Toronto"],"href":"DPSOLVE-2026-07-18.html#talk:658"},{"abstractId":659,"title":"Domain-Independent Dynamic Programming with Constraint Propagation","authors":"Imko Marijnissen, J. Christopher Beck, Emir Demirovic, Ryo Kuroiwa","abstract":"","sessionName":"Talks 1","day":"18/07/2026","startTime":"11:00","affiliations":["Delft","University of Toronto","Unkown"],"href":"DPSOLVE-2026-07-18.html#talk:659"},{"abstractId":660,"title":"Search Strategies for CODD","authors":"Eli Shattuck, Laurent Michel, Willem-Jan van Hoeve","abstract":"","sessionName":"Talks 1","day":"18/07/2026","startTime":"11:00","affiliations":["School of Computing, University of Connecticut, Storrs, CT, USA","Tepper School of Business, Carnegie Mellon University, Pittsburgh, PA, USA"],"href":"DPSOLVE-2026-07-18.html#talk:660"},{"abstractId":661,"title":"Dynamic Programming for Optimal Decision Trees","authors":"Koos van der Linden","abstract":"","sessionName":"Talks 1","day":"18/07/2026","startTime":"11:00","affiliations":["Delft University"],"href":"DPSOLVE-2026-07-18.html#talk:661"},{"abstractId":662,"title":"GPU-Accelerated State Expansion for Anytime Exact Decision-Diagram Search","authors":"Fabio Tardivo, Laurent Michel","abstract":"","sessionName":"Talks 2","day":"18/07/2026","startTime":"14:00","affiliations":["UNKNOWN","UCONN"],"href":"DPSOLVE-2026-07-18.html#talk:662"},{"abstractId":663,"title":"CP or DP? Why Not Both: A Case Study in the Partial Shop Scheduling Problem.","authors":"Emma Legrand, Roger Kameugne, Pierre Schaus","abstract":"","sessionName":"Talks 2","day":"18/07/2026","startTime":"14:00","affiliations":["UCLouvain"],"href":"DPSOLVE-2026-07-18.html#talk:663"},{"abstractId":664,"title":"Decision Diagram-Based Exact Optimization for Assembly Line Balancing with Human-Robot Collaboration","authors":"Jiaxin Zhang, Yiting Sun, Roger Kameugne, Pierre Schaus","abstract":"","sessionName":"Talks 2","day":"18/07/2026","startTime":"14:00","affiliations":["College of Management and Economics, Tianjin University, Tianjin, China","UCLouvain"],"href":"DPSOLVE-2026-07-18.html#talk:664"},{"abstractId":665,"title":"Column Elimination Applied to Scheduling Problems","authors":"Vianney Copp\u00E9","abstract":"","sessionName":"Talks 2","day":"18/07/2026","startTime":"14:00","affiliations":["Hexaly"],"href":"DPSOLVE-2026-07-18.html#talk:665"}]}